odoo/addons/delivery_carrier_info/README.rst
odoo/addons/delivery_carrier_info/__init__.py
odoo/addons/delivery_carrier_info/__manifest__.py
odoo/addons/delivery_carrier_info/i18n/delivery_carrier_info.pot
odoo/addons/delivery_carrier_info/i18n/es.po
odoo/addons/delivery_carrier_info/models/__init__.py
odoo/addons/delivery_carrier_info/models/delivery_carrier.py
odoo/addons/delivery_carrier_info/readme/CONTRIBUTORS.rst
odoo/addons/delivery_carrier_info/readme/DESCRIPTION.rst
odoo/addons/delivery_carrier_info/readme/USAGE.rst
odoo/addons/delivery_carrier_info/static/description/icon.png
odoo/addons/delivery_carrier_info/static/description/index.html
odoo/addons/delivery_carrier_info/views/delivery_view.xml
odoo13_addon_delivery_carrier_info-13.0.1.0.1.dev6.dist-info/METADATA
odoo13_addon_delivery_carrier_info-13.0.1.0.1.dev6.dist-info/WHEEL
odoo13_addon_delivery_carrier_info-13.0.1.0.1.dev6.dist-info/top_level.txt
odoo13_addon_delivery_carrier_info-13.0.1.0.1.dev6.dist-info/RECORD
